{"ongoing_trials": {}, "hyperparameters": {"space": [{"class_name": "Int", "config": {"name": "dense_units", "default": 256, "conditions": [], "min_value": 256, "max_value": 512, "step": 64, "sampling": "linear"}}, {"class_name": "Float", "config": {"name": "dropout_rate", "default": 0.2, "conditions": [], "min_value": 0.2, "max_value": 0.4, "step": 0.1, "sampling": "linear"}}, {"class_name": "Float", "config": {"name": "learning_rate", "default": 0.0001, "conditions": [], "min_value": 1e-05, "max_value": 0.001, "step": null, "sampling": "log"}}], "values": {"dense_units": 256, "dropout_rate": 0.2, "learning_rate": 0.0001}}, "start_order": ["0", "1", "2", "3", "4"], "end_order": ["0", "1", "2", "3", "4"], "run_times": {"0": 1, "1": 1, "2": 1, "3": 1, "4": 1}, "retry_queue": [], "seed": 6557, "seed_state": 6572, "tried_so_far": ["649b0af8c9dc3b1785c512708e2807ed", "8e1896a4b9fdbd23ce1fbaea709f291b", "9ded2ea3c26f0fe9bc6d241f09af6342", "7f3615e35b8fc126a27dd1b3eb3fd9fe", "e9469d0a491906643a81cfaa2a98a2be"], "id_to_hash": {"0": "7f3615e35b8fc126a27dd1b3eb3fd9fe", "1": "9ded2ea3c26f0fe9bc6d241f09af6342", "2": "e9469d0a491906643a81cfaa2a98a2be", "3": "8e1896a4b9fdbd23ce1fbaea709f291b", "4": "649b0af8c9dc3b1785c512708e2807ed"}, "display": {"search_start": "2025-03-13T08:14:43.195048", "trial_start": {"0": "2025-03-13T08:14:43.195048", "1": "2025-03-13T09:29:48.037393", "2": "2025-03-13T11:08:02.968965", "3": "2025-03-13T12:02:34.073358", "4": "2025-03-13T13:32:05.688487"}, "trial_number": {"0": 1, "1": 2, "2": 3, "3": 4, "4": 5}}}